Metadata-Version: 1.0
Name: Trip-advisor
Version: 0.0.1
Summary: Mock packages that allows to get information about hotels
Home-page: UNKNOWN
Author: UNKNOWN
Author-email: UNKNOWN
License: UNKNOWN
Platform: UNKNOWN
